{
  "date": "2024-08-26T15:58:00.000Z",
  "excerpt": "Working",
  "html": "<p>The building remembers PPR<br>\nBut I can have a cable<br>\nThere is just one camera<br>\nHospice for crazy people<br>\nThe beetle rolls his ball<br>\nThere is a lot of unknowns<br>\nAs well as a lot of<br>\nPlain open passages<br>\nGrain of doubt hurts the heart<br>\nBut I will live on<br>\nLike an experienced passenger<br>\nOn the Milky Way high way<br>\nFor now I inhale open space<br>\nIn between i smoke cigarettes<br>\nThe tapeworm consumes it’s victim<br>\nSlowly but consequentially</p>\n",
  "layout": "default.njk",
  "tags": ["meta","post"],
  "title": "Beetles and tapeworms"
}
