{
  "date": "2024-03-10T15:55:00.000Z",
  "excerpt": "Następny",
  "html": "<p>Stracone marzenia<br>\nStracone plany<br>\nKażdy ma to gdzieś<br>\nUżywają siły<br>\nJak rozbite okno<br>\nZniewolony poeta<br>\nNòż w serce<br>\nŁza w ciemności<br>\nPisanie aby pisaċ<br>\nPisanie aby przetrwać<br>\nAby istnieć<br>\nI to uzasadnić<br>\nNa koniec Bóg pamięta<br>\nSpiż tego nie zmieni<br>\nObróci się w proch<br>\nJak wszystko inne</p>\n",
  "layout": "default.njk",
  "tags": ["meta","post"],
  "title": "(PL) Marzenia"
}
