{
  "date": "2024-04-16T14:37:00.000Z",
  "excerpt": "Next",
  "html": "<p>Loud explosion<br>\nTurns a building into rubble<br>\nEveryone dies<br>\nDeath harvests<br>\nMothers mourn their children<br>\nWives husbands<br>\nAt necropolises<br>\nPriests are reading books<br>\nOrphaned children<br>\nGo to orphanages<br>\nFor them<br>\nTheir life is ruined<br>\nA silent observer<br>\nIs smoking a cigarette<br>\nNo miracle<br>\nPlease, call me cold hearted</p>\n",
  "layout": "default.njk",
  "tags": ["meta","post"],
  "title": "Observer"
}
