{
  "date": "2025-04-15T13:25:00.000Z",
  "excerpt": "And a cross",
  "html": "<p>Like slide on a smooth wave<br>\nShine of stars at dark night<br>\nChirping of birds at spring<br>\nSpring full of sun rays<br>\nGlance of expensive diamonds<br>\nLack of cheap tears<br>\nSip of water during heat<br>\nHeat that is so common<br>\nIron cross smashed into the ground<br>\nHeretic kicked by the mob<br>\nPeon eating meat<br>\nEating with his bear hands<br>\nRotting corpse of a horse<br>\nFull of crawling maggots<br>\nDog biting a dog<br>\nA man laughing out loud</p>\n",
  "layout": "default.njk",
  "tags": ["meta","post"],
  "title": "Slide"
}
